README.rst
setup.cfg
setup.py
opengraph/__init__.py
opengraph/opengraph.py
python_opengraph.egg-info/PKG-INFO
python_opengraph.egg-info/SOURCES.txt
python_opengraph.egg-info/dependency_links.txt
python_opengraph.egg-info/requires.txt
python_opengraph.egg-info/top_level.txt