Metadata-Version: 1.1
Name: python-opengraph
Version: 0.0.2
Summary: Python module to parse Open Graph metadata on web pages
Home-page: https://github.com/HenrikOssipoff/python-opengraph
Author: Henrik Ossipoff Hansen
Author-email: henrik.ossipoff@gmail.com
License: MIT
Platform: UNKNOWN
Classifier: Development Status :: 1 - Planning
Classifier: Intended Audience :: Developers
Classifier: License :: OSI Approved :: MIT License
Classifier: Operating System :: OS Independent
Classifier: Programming Language :: Python :: 2
Classifier: Programming Language :: Python :: 2.7
Classifier: Programming Language :: Python :: 3
Classifier: Programming Language :: Python :: 3.3
Classifier: Programming Language :: Python :: 3.4
Classifier: Programming Language :: Python :: Implementation :: PyPy
